achain/__init__.py
achain/chain.py
achain/exceptions/__init__.py
achain/exceptions/step.py
achain/steps/__init__.py
achain/steps/action.py
achain/steps/base.py
achain/steps/conditional.py
achain/steps/exception.py
achain/steps/multi.py
achain/utilities/__init__.py
achain/utilities/common.py
achain-0.1.1.dist-info/LICENSE
achain-0.1.1.dist-info/METADATA
achain-0.1.1.dist-info/WHEEL
achain-0.1.1.dist-info/top_level.txt
achain-0.1.1.dist-info/RECORD
