Metadata-Version: 2.1
Name: achain
Version: 0.1.1
Summary: Library used for chaining together synchronous and asynchronous functions for data transformation
Author-email: "Christopher O. Tubbs" <christopherotubbs@gmail.com>
License: MIT License
Project-URL: Homepage, https://github.com/christophertubbs/achain
Project-URL: Issues, https://github.com/christophertubbs/achain/issues
Classifier: Development Status :: 3 - Alpha
Classifier: Intended Audience :: Developers
Classifier: License :: OSI Approved :: MIT License
Classifier: Programming Language :: Python :: 3.8
Classifier: Programming Language :: Python :: 3.9
Classifier: Programming Language :: Python :: 3.10
Classifier: Programming Language :: Python :: 3.11
Classifier: Programming Language :: Python :: 3.12
Classifier: Topic :: Software Development :: Libraries
Classifier: Operating System :: OS Independent
Classifier: Topic :: Software Development :: Libraries
Requires-Python: >=3.8
License-File: LICENSE
Requires-Dist: pydantic>=2.8.2
Requires-Dist: typing-extensions
Provides-Extra: dev
Requires-Dist: pytest; extra == "dev"
